opentelemetry/util/genai/__init__.py
opentelemetry/util/genai/attributes.py
opentelemetry/util/genai/callbacks.py
opentelemetry/util/genai/config.py
opentelemetry/util/genai/debug.py
opentelemetry/util/genai/environment_variables.py
opentelemetry/util/genai/handler.py
opentelemetry/util/genai/instruments.py
opentelemetry/util/genai/interfaces.py
opentelemetry/util/genai/plugins.py
opentelemetry/util/genai/span_context.py
opentelemetry/util/genai/types.py
opentelemetry/util/genai/upload_hook.py
opentelemetry/util/genai/utils.py
opentelemetry/util/genai/version.py
opentelemetry/util/genai/_fsspec_upload/__init__.py
opentelemetry/util/genai/_fsspec_upload/fsspec_hook.py
opentelemetry/util/genai/emitters/__init__.py
opentelemetry/util/genai/emitters/composite.py
opentelemetry/util/genai/emitters/configuration.py
opentelemetry/util/genai/emitters/content_events.py
opentelemetry/util/genai/emitters/evaluation.py
opentelemetry/util/genai/emitters/metrics.py
opentelemetry/util/genai/emitters/span.py
opentelemetry/util/genai/emitters/spec.py
opentelemetry/util/genai/emitters/utils.py
splunk_otel_util_genai-0.1.9.dist-info/METADATA
splunk_otel_util_genai-0.1.9.dist-info/WHEEL
splunk_otel_util_genai-0.1.9.dist-info/entry_points.txt
splunk_otel_util_genai-0.1.9.dist-info/licenses/LICENSE
splunk_otel_util_genai-0.1.9.dist-info/RECORD
